vsquickview/__init__.py
vsquickview/colourbars.py
vsquickview/fakevsquickview.py
vsquickview/vsquickview.py
vsquickview/vsquickview.qml
vsquickview-1.1.5.dist-info/METADATA
vsquickview-1.1.5.dist-info/WHEEL
vsquickview-1.1.5.dist-info/licenses/LICENSE
vsquickview-1.1.5.dist-info/RECORD
