Metadata-Version: 2.4
Name: vsquickview
Version: 1.1.5
Summary: VapourSynth preview script for Jupyter Notebook
Project-URL: Documentation, https://github.com/Akatmks/vsquickview
Project-URL: Issues, https://github.com/Akatmks/vsquickview/issues
Project-URL: Source, https://github.com/Akatmks/vsquickview
Author-email: Akatsumekusa <Akatsumekusa@protonmail.com>
License-Expression: MIT
License-File: LICENSE
Keywords: VapourSynth
Classifier: License :: OSI Approved :: MIT License
Classifier: Programming Language :: Python
Classifier: Programming Language :: Python :: 3.8
Classifier: Programming Language :: Python :: 3.9
Classifier: Programming Language :: Python :: 3.10
Classifier: Programming Language :: Python :: 3.11
Classifier: Programming Language :: Python :: 3.12
Classifier: Topic :: Multimedia :: Video
Requires-Python: >=3.8
Requires-Dist: numpy
Requires-Dist: pyside6
